{"type":"FeatureCollection","crs":{"type":"name","properties":{"name":"EPSG:4326"}},"features":[{"type":"Feature","id":213,"geometry":{"type":"Point","coordinates":[73.003074943916729,20.271776018969959]},"properties":{"OBJECTID":213,"STNAME":"DADRA & NAGAR HAVE","DTNAME":"Dadra & Nagar Haveli","DIST_HQ":"Silvassa","STATE_HQ":1,"STCODE11":"26","DTCODE11":"496","YEAR_STAT":"2011_c","DIST_HQNM":"Silvassa","Dist_LGD":465,"LOC_STAT_1":"District Hq","LOC_NAME":"Dadra & Nagar Haveli"}}]}