{"type":"FeatureCollection","crs":{"type":"name","properties":{"name":"EPSG:4326"}},"features":[{"type":"Feature","id":2002,"geometry":{"type":"Point","coordinates":[73.004534480776286,20.275676751371439]},"properties":{"OBJECTID":2002,"stname":"DADRA & NAGAR HAVE","dtname":"Dadra & Nagar Haveli","STCODE11":"26","DTCODE11":"496","SDTCODE11":"03949","NAME11":"Dadra & Nagar Haveli","LOC_NAME":"Dadra & Nagar Haveli"}}]}